pymacaroons2/__init__.py
pymacaroons2/async_verifier.py
pymacaroons2/caveat.py
pymacaroons2/exceptions.py
pymacaroons2/macaroon.py
pymacaroons2/utils.py
pymacaroons2/verifier.py
pymacaroons2/binders/__init__.py
pymacaroons2/binders/base_binder.py
pymacaroons2/binders/hash_signatures_binder.py
pymacaroons2/caveat_delegates/__init__.py
pymacaroons2/caveat_delegates/base_first_party.py
pymacaroons2/caveat_delegates/base_third_party.py
pymacaroons2/caveat_delegates/encrypted_first_party.py
pymacaroons2/caveat_delegates/first_party.py
pymacaroons2/caveat_delegates/third_party.py
pymacaroons2/field_encryptors/__init__.py
pymacaroons2/field_encryptors/base_field_encryptor.py
pymacaroons2/field_encryptors/secret_box_encryptor.py
pymacaroons2/serializers/__init__.py
pymacaroons2/serializers/base_serializer.py
pymacaroons2/serializers/binary_serializer.py
pymacaroons2/serializers/json_serializer.py
pymacaroons2-2.0.3.dist-info/licenses/LICENSE
pymacaroons2-2.0.3.dist-info/METADATA
pymacaroons2-2.0.3.dist-info/WHEEL
pymacaroons2-2.0.3.dist-info/top_level.txt
pymacaroons2-2.0.3.dist-info/RECORD
