Metadata-Version: 2.4
Name: pymacaroons2
Version: 2.0.3
Summary: Fast, secure Macaroon library for Python 3.8+ with optional Rust acceleration
Author-email: Tazkia Nizami <tazkia.nizami@gmail.com>, Evan Cordell <evancordell@gmail.com>
License: MIT
Project-URL: Homepage, https://github.com/TazakiN/pymacaroons2
Project-URL: Repository, https://github.com/TazakiN/pymacaroons2.git
Project-URL: Documentation, https://github.com/TazakiN/pymacaroons2#readme
Project-URL: Changelog, https://github.com/TazakiN/pymacaroons2/blob/main/CHANGELOG.md
Project-URL: Issues, https://github.com/TazakiN/pymacaroons2/issues
Keywords: macaroon,macaroons,authentication,authorization,security,token,bearer-token,capability,caveat
Classifier: Development Status :: 5 - Production/Stable
Classifier: Intended Audience :: Developers
Classifier: License :: OSI Approved :: MIT License
Classifier: Operating System :: OS Independent
Classifier: Programming Language :: Python :: 3
Classifier: Programming Language :: Python :: 3.8
Classifier: Programming Language :: Python :: 3.9
Classifier: Programming Language :: Python :: 3.10
Classifier: Programming Language :: Python :: 3.11
Classifier: Programming Language :: Python :: 3.12
Classifier: Programming Language :: Python :: 3.13
Classifier: Programming Language :: Rust
Classifier: Topic :: Security
Classifier: Topic :: Security :: Cryptography
Classifier: Topic :: Software Development :: Libraries :: Python Modules
Classifier: Typing :: Typed
Requires-Python: >=3.8
License-File: LICENSE
Requires-Dist: cryptography>=3.4.8
Provides-Extra: encryption
Requires-Dist: pynacl>=1.5.0; extra == "encryption"
Provides-Extra: rust
Provides-Extra: dev
Requires-Dist: pytest>=7.0; extra == "dev"
Requires-Dist: pytest-benchmark>=4.0; extra == "dev"
Requires-Dist: pytest-asyncio>=0.21; extra == "dev"
Requires-Dist: pytest-cov>=4.0; extra == "dev"
Requires-Dist: hypothesis>=6.0; extra == "dev"
Requires-Dist: black>=22.0; extra == "dev"
Requires-Dist: isort>=5.10; extra == "dev"
Requires-Dist: mypy>=1.0; extra == "dev"
Requires-Dist: pre-commit>=2.20; extra == "dev"
Requires-Dist: pynacl>=1.5.0; extra == "dev"
Requires-Dist: maturin>=1.0; extra == "dev"
Provides-Extra: all
Requires-Dist: pynacl>=1.5.0; extra == "all"
Dynamic: license-file
